pyanalyze/__init__.py
pyanalyze/__main__.py
pyanalyze/analysis_lib.py
pyanalyze/annotated_types.py
pyanalyze/annotations.py
pyanalyze/arg_spec.py
pyanalyze/ast_annotator.py
pyanalyze/asynq_checker.py
pyanalyze/attributes.py
pyanalyze/boolability.py
pyanalyze/checker.py
pyanalyze/error_code.py
pyanalyze/extensions.py
pyanalyze/find_unused.py
pyanalyze/format_strings.py
pyanalyze/functions.py
pyanalyze/implementation.py
pyanalyze/importer.py
pyanalyze/name_check_visitor.py
pyanalyze/node_visitor.py
pyanalyze/options.py
pyanalyze/patma.py
pyanalyze/predicates.py
pyanalyze/reexport.py
pyanalyze/runtime.py
pyanalyze/safe.py
pyanalyze/shared_options.py
pyanalyze/signature.py
pyanalyze/stacked_scopes.py
pyanalyze/suggested_type.py
pyanalyze/test.toml
pyanalyze/test_analysis_lib.py
pyanalyze/test_annotated_types.py
pyanalyze/test_annotations.py
pyanalyze/test_arg_spec.py
pyanalyze/test_ast_annotator.py
pyanalyze/test_async_await.py
pyanalyze/test_asynq.py
pyanalyze/test_asynq_checker.py
pyanalyze/test_attributes.py
pyanalyze/test_boolability.py
pyanalyze/test_config.py
pyanalyze/test_definite_value.py
pyanalyze/test_deprecated.py
pyanalyze/test_enum.py
pyanalyze/test_error_code.py
pyanalyze/test_extensions.py
pyanalyze/test_format_strings.py
pyanalyze/test_functions.py
pyanalyze/test_generators.py
pyanalyze/test_implementation.py
pyanalyze/test_import.py
pyanalyze/test_inference_helpers.py
pyanalyze/test_literal_string.py
pyanalyze/test_name_check_visitor.py
pyanalyze/test_never.py
pyanalyze/test_node_visitor.py
pyanalyze/test_operations.py
pyanalyze/test_override.py
pyanalyze/test_patma.py
pyanalyze/test_pep673.py
pyanalyze/test_recursion.py
pyanalyze/test_runtime.py
pyanalyze/test_self.py
pyanalyze/test_signature.py
pyanalyze/test_stacked_scopes.py
pyanalyze/test_suggested_type.py
pyanalyze/test_thrift_enum.py
pyanalyze/test_try.py
pyanalyze/test_type_aliases.py
pyanalyze/test_type_evaluation.py
pyanalyze/test_type_object.py
pyanalyze/test_typeddict.py
pyanalyze-0.13.1.dist-info/LICENSE
pyanalyze-0.13.1.dist-info/METADATA
pyanalyze-0.13.1.dist-info/WHEEL
pyanalyze-0.13.1.dist-info/entry_points.txt
pyanalyze-0.13.1.dist-info/top_level.txt
pyanalyze-0.13.1.dist-info/RECORD
