Metadata-Version: 2.1
Name: pyanalyze
Version: 0.13.1
Summary: A static analyzer for Python
Home-page: https://github.com/quora/pyanalyze
Author: Quora, Inc.
Author-email: jelle@quora.com
License: Apache Software License
Keywords: quora static analysis
Classifier: License :: OSI Approved :: Apache Software License
Classifier: Programming Language :: Python
Classifier: Programming Language :: Python :: 3.8
Classifier: Programming Language :: Python :: 3.9
Classifier: Programming Language :: Python :: 3.10
Classifier: Programming Language :: Python :: 3.11
Classifier: Programming Language :: Python :: 3.12
Requires-Python: >=3.8
License-File: LICENSE
Requires-Dist: asynq
Requires-Dist: qcore>=0.5.1
Requires-Dist: ast-decompiler>=0.4.0
Requires-Dist: typeshed-client>=2.1.0
Requires-Dist: typing-extensions>=4.12.0
Requires-Dist: codemod
Requires-Dist: tomli>=1.1.0
Provides-Extra: tests
Requires-Dist: pytest; extra == "tests"
Requires-Dist: mypy-extensions; extra == "tests"
Requires-Dist: attrs; extra == "tests"
Requires-Dist: pydantic; extra == "tests"
Requires-Dist: annotated-types; extra == "tests"
